<annotation>
	<folder>imagenes gorila</folder>
	<filename>1937.jpg</filename>
	<path>/home/kevin/Escritorio/imagenes gorila/1937.jpg</path>
	<source>
		<database>Unknown</database>
	</source>
	<size>
		<width>183</width>
		<height>276</height>
		<depth>3</depth>
	</size>
	<segmented>0</segmented>
	<object>
		<name>Gorila</name>
		<pose>Unspecified</pose>
		<truncated>0</truncated>
		<difficult>0</difficult>
		<bndbox>
			<xmin>33</xmin>
			<ymin>52</ymin>
			<xmax>156</xmax>
			<ymax>260</ymax>
		</bndbox>
	</object>
</annotation>
